pytipeee/__init__.py
pytipeee/pytipeee.py
pytipeee-1.1.6.dist-info/LICENSE
pytipeee-1.1.6.dist-info/METADATA
pytipeee-1.1.6.dist-info/WHEEL
pytipeee-1.1.6.dist-info/top_level.txt
pytipeee-1.1.6.dist-info/RECORD
