Metadata-Version: 2.1
Name: pytipeee
Version: 1.1.6
Summary: Python scraper for tipeee
Home-page: https://github.com/alberts96/pytipeee
Author: Carlo Alberto Carrucciu
Author-email: carloalbertocarrucciu@outlook.it
License: UNKNOWN
Project-URL: Bug Tracker, https://github.com/alberts96/pytipeee/issues
Platform: UNKNOWN
Classifier: Programming Language :: Python :: 3
Classifier: License :: OSI Approved :: MIT License
Classifier: Operating System :: OS Independent
Requires-Python: >=3.6
License-File: LICENSE
